{
  "TUI": "7008dcf5-a91c-4a7d-80ba-989e6792df0c|b4db34a7-6217-454b-aaf1-3e30d68badbb|20250410123225",
  "CurrencyCode": "INR",
  "PaidSSR": true,
  "Trips": [
    {
      "From": "DEL",
      "To": "BLR",
      "Journey": [
        {
          "Provider": "6E",
          "MultiSSR": "",
          "ConversationID": "",
          "IsWebCheckInAvailable": false,
          "WebCheckInMessage": null,
          "Segments": [
            {
              "FUID": "",
              "VAC": "6E",
              "Index": null,
              "SSR": [
                {
                  "Code": "XBPE",
                  "Description": "Prepaid Excess Baggage – 3 Kg",
                  "PieceDescription": "",
                  "Charge": -165.0,
                  "VAT": 0.0,
                  "Type": "2",
                  "Category": "",
                  "PTC": "",
                  "ID": 2,
                  "IsFreeMeal": false,
                  "MealImage": "",
                  "SSRUrl": null,
                  "OriginalCurrencyCharge": 0.0,
                  "SSRSubCode": "",
                  "SSRTaxcharge": 0.0,
                  "SSRNetAmount": -165.0,
                  "Discount": 0.0,
                  "AdditionalFields": null
                },
                {
                  "Code": "CPML",
                  "Description": "Meal Code",
                  "PieceDescription": "",
                  "Charge": 0.0,
                  "VAT": 0.0,
                  "Type": "1",
                  "Category": "",
                  "PTC": "",
                  "ID": 13,
                  "IsFreeMeal": false,
                  "MealImage": "",
                  "SSRUrl": null,
                  "OriginalCurrencyCharge": 0.0,
                  "SSRSubCode": "",
                  "SSRTaxcharge": 0.0,
                  "SSRNetAmount": 0.0,
                  "Discount": 0.0,
                  "AdditionalFields": null
                },
                {
                  "Code": "TCSW",
                  "Description": "Tomato Cucumber Cheese Lettuce Sandwich Combo",
                  "PieceDescription": "",
                  "Charge": 10.0,
                  "VAT": 0.0,
                  "Type": "1",
                  "Category": "",
                  "PTC": "",
                  "ID": 8,
                  "IsFreeMeal": false,
                  "MealImage": "",
                  "SSRUrl": null,
                  "OriginalCurrencyCharge": 0.0,
                  "SSRSubCode": "",
                  "SSRTaxcharge": 0.0,
                  "SSRNetAmount": 10.0,
                  "Discount": 0.0,
                  "AdditionalFields": null
                },
                {
                  "Code": "CNWT",
                  "Description": "CASHEW (SALTED) 50 GMS",
                  "PieceDescription": "",
                  "Charge": 300.0,
                  "VAT": 0.0,
                  "Type": "1",
                  "Category": "",
                  "PTC": "",
                  "ID": 14,
                  "IsFreeMeal": false,
                  "MealImage": "",
                  "SSRUrl": null,
                  "OriginalCurrencyCharge": 0.0,
                  "SSRSubCode": "",
                  "SSRTaxcharge": 0.0,
                  "SSRNetAmount": 300.0,
                  "Discount": 0.0,
                  "AdditionalFields": null
                },
                {
                  "Code": "VCSW",
                  "Description": "6E Eats choice of the day (veg) + beverage",
                  "PieceDescription": "",
                  "Charge": 400.0,
                  "VAT": 0.0,
                  "Type": "1",
                  "Category": "",
                  "PTC": "",
                  "ID": 7,
                  "IsFreeMeal": false,
                  "MealImage": "",
                  "SSRUrl": null,
                  "OriginalCurrencyCharge": 0.0,
                  "SSRSubCode": "",
                  "SSRTaxcharge": 0.0,
                  "SSRNetAmount": 400.0,
                  "Discount": 0.0,
                  "AdditionalFields": null
                },
                {
                  "Code": "AGSW",
                  "Description": "#IndiaByIndiGo regional favourite (veg) + beverage",
                  "PieceDescription": "",
                  "Charge": 400.0,
                  "VAT": 0.0,
                  "Type": "1",
                  "Category": "",
                  "PTC": "",
                  "ID": 16,
                  "IsFreeMeal": false,
                  "MealImage": "",
                  "SSRUrl": null,
                  "OriginalCurrencyCharge": 0.0,
                  "SSRSubCode": "",
                  "SSRTaxcharge": 0.0,
                  "SSRNetAmount": 400.0,
                  "Discount": 0.0,
                  "AdditionalFields": null
                },
                {
                  "Code": "FFWD",
                  "Description": "Priority Check-In",
                  "PieceDescription": "",
                  "Charge": 495.0,
                  "VAT": 0.0,
                  "Type": "8",
                  "Category": "",
                  "PTC": "",
                  "ID": 12,
                  "IsFreeMeal": false,
                  "MealImage": "",
                  "SSRUrl": null,
                  "OriginalCurrencyCharge": 0.0,
                  "SSRSubCode": "",
                  "SSRTaxcharge": 0.0,
                  "SSRNetAmount": 495.0,
                  "Discount": 0.0,
                  "AdditionalFields": null
                },
                {
                  "Code": "CJSW",
                  "Description": "Chicken Junglee Sandwich Combo",
                  "PieceDescription": "",
                  "Charge": 500.0,
                  "VAT": 0.0,
                  "Type": "1",
                  "Category": "",
                  "PTC": "",
                  "ID": 15,
                  "IsFreeMeal": false,
                  "MealImage": "",
                  "SSRUrl": null,
                  "OriginalCurrencyCharge": 0.0,
                  "SSRSubCode": "",
                  "SSRTaxcharge": 0.0,
                  "SSRNetAmount": 500.0,
                  "Discount": 0.0,
                  "AdditionalFields": null
                },
                {
                  "Code": "IXBA",
                  "Description": "International Connections Baggage - 8kgs",
                  "PieceDescription": "",
                  "Charge": 1600.0,
                  "VAT": 0.0,
                  "Type": "2",
                  "Category": "ICXB",
                  "PTC": "",
                  "ID": 11,
                  "IsFreeMeal": false,
                  "MealImage": "",
                  "SSRUrl": null,
                  "OriginalCurrencyCharge": 0.0,
                  "SSRSubCode": "",
                  "SSRTaxcharge": 0.0,
                  "SSRNetAmount": 1600.0,
                  "Discount": 0.0,
                  "AdditionalFields": null
                },
                {
                  "Code": "XBPA",
                  "Description": "Prepaid Excess Baggage – 5 Kg",
                  "PieceDescription": "",
                  "Charge": 2250.0,
                  "VAT": 0.0,
                  "Type": "2",
                  "Category": "",
                  "PTC": "",
                  "ID": 6,
                  "IsFreeMeal": false,
                  "MealImage": "",
                  "SSRUrl": null,
                  "OriginalCurrencyCharge": 0.0,
                  "SSRSubCode": "",
                  "SSRTaxcharge": 0.0,
                  "SSRNetAmount": 2250.0,
                  "Discount": 0.0,
                  "AdditionalFields": null
                },
                {
                  "Code": "IXBB",
                  "Description": "International Connections Baggage - 15kgs",
                  "PieceDescription": "",
                  "Charge": 3000.0,
                  "VAT": 0.0,
                  "Type": "2",
                  "Category": "ICXB",
                  "PTC": "",
                  "ID": 10,
                  "IsFreeMeal": false,
                  "MealImage": "",
                  "SSRUrl": null,
                  "OriginalCurrencyCharge": 0.0,
                  "SSRSubCode": "",
                  "SSRTaxcharge": 0.0,
                  "SSRNetAmount": 3000.0,
                  "Discount": 0.0,
                  "AdditionalFields": null
                },
                {
                  "Code": "XBPB",
                  "Description": "Prepaid Excess Baggage – 10 Kg ",
                  "PieceDescription": "",
                  "Charge": 4500.0,
                  "VAT": 0.0,
                  "Type": "2",
                  "Category": "",
                  "PTC": "",
                  "ID": 5,
                  "IsFreeMeal": false,
                  "MealImage": "",
                  "SSRUrl": null,
                  "OriginalCurrencyCharge": 0.0,
                  "SSRSubCode": "",
                  "SSRTaxcharge": 0.0,
                  "SSRNetAmount": 4500.0,
                  "Discount": 0.0,
                  "AdditionalFields": null
                },
                {
                  "Code": "XBPC",
                  "Description": "Prepaid Excess Baggage – 15 Kg",
                  "PieceDescription": "",
                  "Charge": 5630.0,
                  "VAT": 0.0,
                  "Type": "2",
                  "Category": "",
                  "PTC": "",
                  "ID": 4,
                  "IsFreeMeal": false,
                  "MealImage": "",
                  "SSRUrl": null,
                  "OriginalCurrencyCharge": 0.0,
                  "SSRSubCode": "",
                  "SSRTaxcharge": 0.0,
                  "SSRNetAmount": 5630.0,
                  "Discount": 0.0,
                  "AdditionalFields": null
                },
                {
                  "Code": "IXBC",
                  "Description": "International Connections Baggage - 30kgs",
                  "PieceDescription": "",
                  "Charge": 6000.0,
                  "VAT": 0.0,
                  "Type": "2",
                  "Category": "ICXB",
                  "PTC": "",
                  "ID": 9,
                  "IsFreeMeal": false,
                  "MealImage": "",
                  "SSRUrl": null,
                  "OriginalCurrencyCharge": 0.0,
                  "SSRSubCode": "",
                  "SSRTaxcharge": 0.0,
                  "SSRNetAmount": 6000.0,
                  "Discount": 0.0,
                  "AdditionalFields": null
                },
                {
                  "Code": "XBPJ",
                  "Description": "Prepaid Excess Baggage - 20Kg",
                  "PieceDescription": "",
                  "Charge": 7500.0,
                  "VAT": 0.0,
                  "Type": "2",
                  "Category": "",
                  "PTC": "",
                  "ID": 1,
                  "IsFreeMeal": false,
                  "MealImage": "",
                  "SSRUrl": null,
                  "OriginalCurrencyCharge": 0.0,
                  "SSRSubCode": "",
                  "SSRTaxcharge": 0.0,
                  "SSRNetAmount": 7500.0,
                  "Discount": 0.0,
                  "AdditionalFields": null
                },
                {
                  "Code": "XBPD",
                  "Description": "Prepaid Excess Baggage – 30 Kg",
                  "PieceDescription": "",
                  "Charge": 11250.0,
                  "VAT": 0.0,
                  "Type": "2",
                  "Category": "",
                  "PTC": "",
                  "ID": 3,
                  "IsFreeMeal": false,
                  "MealImage": "",
                  "SSRUrl": null,
                  "OriginalCurrencyCharge": 0.0,
                  "SSRSubCode": "",
                  "SSRTaxcharge": 0.0,
                  "SSRNetAmount": 11250.0,
                  "Discount": 0.0,
                  "AdditionalFields": null
                }
              ]
            }
          ]
        }
      ]
    }
  ],
  "Code": "200",
  "Msg": [ "Success" ]
}